mysql_server_ddz/__init__.py
mysql_server_ddz-0.1.2.dist-info/WHEEL
mysql_server_ddz-0.1.2.dist-info/entry_points.txt
mysql_server_ddz-0.1.2.dist-info/METADATA
mysql_server_ddz-0.1.2.dist-info/RECORD
