Metadata-Version: 2.3
Name: mysql-server-ddz
Version: 0.1.2
Summary: Add your description here
Author: LOVEDDZ
Author-email: LOVEDDZ <1584934130@qq.com>
Requires-Dist: mcp[cli]>=1.25.0
Requires-Python: >=3.14.2
